zbToolLib/__init__.py
zbToolLib/data.py
zbToolLib/file.py
zbToolLib/info.py
zbToolLib/log.py
zbToolLib/system.py
zbToolLib/web.py
zbtoollib-2.0.7.dist-info/licenses/LICENSE
zbtoollib-2.0.7.dist-info/METADATA
zbtoollib-2.0.7.dist-info/WHEEL
zbtoollib-2.0.7.dist-info/top_level.txt
zbtoollib-2.0.7.dist-info/RECORD
