Metadata-Version: 2.4
Name: zbToolLib
Version: 2.0.7
Summary: zb工具库
Author-email: Ianzb <93322252@qq.com>
Maintainer-email: Ianzb <93322252@qq.com>
License: MIT License
Project-URL: Repository, https://github.com/Ianzb/zbToolLib/
Keywords: zb,Ianzb,tool,lib
Classifier: Programming Language :: Python :: 3
Classifier: Programming Language :: Python :: 3.13
Classifier: License :: OSI Approved :: MIT License
Classifier: Operating System :: OS Independent
Classifier: Operating System :: Microsoft :: Windows
Classifier: Operating System :: MacOS :: MacOS X
Classifier: Operating System :: POSIX :: Linux
Requires-Python: >=3.12
License-File: LICENSE
Requires-Dist: send2trash>=1.8.3
Requires-Dist: requests>=2.32.5
Requires-Dist: winshell>=0.6; sys_platform == "win32"
Requires-Dist: pywin32>=311; sys_platform == "win32"
Requires-Dist: puremagic>=1.30
Dynamic: license-file
